djangocms_helper/__init__.py
djangocms_helper/base_test.py
djangocms_helper/default_settings.py
djangocms_helper/main.py
djangocms_helper/runner.py
djangocms_helper/urls.py
djangocms_helper/utils.py
djangocms_helper/locale/en/LC_MESSAGES/django.po
djangocms_helper/test_data/__init__.py
djangocms_helper/test_data/models.py
djangocms_helper/test_data/templates/base.html
djangocms_helper/test_data/templates/fullwidth.html
djangocms_helper/test_data/templates/page.html
djangocms_helper/test_utils/__init__.py
djangocms_helper/test_utils/cms_helper.py
djangocms_helper/test_utils/cms_helper_custom.py
djangocms_helper/test_utils/cms_helper_extra.py
djangocms_helper/test_utils/cms_helper_extra_runner.py
djangocms_helper/test_utils/runners.py
djangocms_helper/test_utils/custom_user/__init__.py
djangocms_helper/test_utils/custom_user/models.py
djangocms_helper/test_utils/example1/__init__.py
djangocms_helper/test_utils/example1/cms_app.py
djangocms_helper/test_utils/example1/cms_apps.py
djangocms_helper/test_utils/example1/cms_plugins.py
djangocms_helper/test_utils/example1/models.py
djangocms_helper/test_utils/example1/data/django.po
djangocms_helper/test_utils/example1/data/django_0001_initial.py
djangocms_helper/test_utils/example1/data/django_0001_partial.py
djangocms_helper/test_utils/example1/data/south_0001_initial.py
djangocms_helper/test_utils/example1/data/south_0001_partial.py
djangocms_helper/test_utils/example1/templates/fake_plugin.html
djangocms_helper/test_utils/example1/templates/cms/plugins/text.html
djangocms_helper/test_utils/example1/tests/__init__.py
djangocms_helper/test_utils/example1/tests/test_fake.py
djangocms_helper/test_utils/example2/__init__.py
djangocms_helper/test_utils/example2/models.py
djangocms_helper/tests/__init__.py
djangocms_helper/tests/test_commands.py
djangocms_helper-1.2.5.dist-info/LICENSE
djangocms_helper-1.2.5.dist-info/METADATA
djangocms_helper-1.2.5.dist-info/WHEEL
djangocms_helper-1.2.5.dist-info/entry_points.txt
djangocms_helper-1.2.5.dist-info/top_level.txt
djangocms_helper-1.2.5.dist-info/RECORD
