Metadata-Version: 2.1
Name: djangocms-helper
Version: 1.2.5
Summary: Helper for django applications development
Home-page: https://github.com/nephila/djangocms-helper
Author: Iacopo Spalletti
Author-email: i.spalletti@nephila.it
License: GPLv2+
Platform: UNKNOWN
Classifier: License :: OSI Approved :: GNU General Public License v2 or later (GPLv2+)
Classifier: Development Status :: 5 - Production/Stable
Classifier: Framework :: Django
Classifier: Framework :: Django :: 1.11
Classifier: Framework :: Django :: 2.0
Classifier: Framework :: Django :: 2.1
Classifier: Framework :: Django :: 2.2
Classifier: Programming Language :: Python
Classifier: Programming Language :: Python :: 2
Classifier: Programming Language :: Python :: 2.7
Classifier: Programming Language :: Python :: 3
Classifier: Programming Language :: Python :: 3.5
Classifier: Programming Language :: Python :: 3.6
Classifier: Programming Language :: Python :: 3.7
Requires-Dist: docopt
Requires-Dist: dj-database-url
Requires-Dist: mock ; python_version<"3.3"
Provides-Extra: cms
Requires-Dist: django-cms (<3.8,>=3.4) ; extra == 'cms'
Provides-Extra: pyflakes
Requires-Dist: pyflakes (<2.1) ; extra == 'pyflakes'
Requires-Dist: django-cms (<3.8,>=3.4) ; extra == 'pyflakes'
